{
  "id": "gan_10909",
  "text": "KINGS NEUROSCIENCES CENTRE\n\nClinic Date: 27 August 2023\n\nDr Patel\nRiverside Health Centre\n\n12 Brook Lane, Southwark, London SE1 5AB\n\nDear Dr Patel,\n\nAmelia Hart, DOB: 14-03-1987, Hospital No: H936502, NHS No. 7482195603\nFlat 3, 27 Willow Court, London SE15 3QT\n\nDiagnoses/summary: Recurrent seizures with ongoing events despite multiple prior therapies. A personalised self-management plan is documented elsewhere in the notes. Prior EEGs and imaging have been reviewed previously; no definitive structural cause identified to date.\n\nCurrent concerns and history: I reviewed Amelia Hart today following reports of variable control over recent weeks. She describes sleep disruption due to shift-pattern work and notes that when sleep is curtailed she experiences clusters of events. Specifically, over the past month she reports six clusters this month; each ~4 focal impaired-awareness seizures. She characterises these as brief episodes of behavioural arrest with automatisms, followed by fatigue and partial recall. She denies generalised convulsive activity, tongue biting, or significant injury. She also reports intermittent morning headaches which she attributes to poor sleep. No recent hospital admissions. A personalised plan for managing cluster patterns has been agreed and is recorded elsewhere in her care plan documentation.\n\nMedication history: She has previously tried levetiracetam, carbamazepine, valproate, gabapentin, phenytoin, phenobarbital, lacosamide, and clobazam with limited durability of benefit and/or side effects (notably fatigue and mood symptoms with some agents). She has not used topiramate, zonisamide, or perampanel. No known drug allergies.\n\nCurrent medications: Lamotrigine 100 mg twice daily; folic acid 5 mg daily; metoclopramide as required for nausea. She uses a reminder app and pill organiser; adherence appears good by her report.\n\nExamination and tests: Neurological examination today was non-focal. Blood pressure 118/72 mmHg, pulse 72 bpm. Weight stable. Recent routine bloods (U&E, LFT, FBC) recorded in primary care last month were within reference ranges. No new imaging performed since prior normal MRI report on file.\n\nDiscussion: We reviewed triggers and her personalised plan, focusing on sleep hygiene, safety during periods of increased risk, and when to seek urgent help. She reports occasional cluster patterns linked to sleep loss and is aware of the early signs. She prefers to optimise non-pharmacological measures first and keep medication options under review. We discussed potential future options, including consideration of agents not yet trialled, and agreed no immediate change today given recent stability between clusters and her wish to continue monitoring.\n\nPlan:\n- Continue current lamotrigine dose for now; no change today.\n- Reinforce sleep and routine measures as per personalised plan; patient has written guidance and emergency contact numbers.\n- Provide seizure diary template integrated with her reminder app; she will document timing relative to sleep and any missed doses.\n- Arrange epilepsy specialist nurse telephone review in 4–6 weeks to reassess frequency and impact of clusters and to revisit treatment choices if events persist.\n- Safety advice updated: bathing supervision avoided, preferred showers; cooking with caution during periods of increased risk; avoid heights and open water when sleep-deprived.\n- Routine clinic follow-up in 4 months, with an option for earlier review if cluster frequency increases or injuries occur.\n\nYours sincerely,",
  "entities": [
    {
      "id": "T_gold",
      "type": "SeizureFrequency",
      "start": 796,
      "end": 895,
      "text": "over the past month she reports six clusters this month; each ~4 focal impaired-awareness seizures.",
      "attributes": {
        "Label": "6 cluster per month, 4 per cluster",
        "Type": "gold"
      }
    },
    {
      "id": "T_ref",
      "type": "SeizureFrequency",
      "start": 828,
      "end": 894,
      "text": "six clusters this month; each ~4 focal impaired-awareness seizures",
      "attributes": {
        "Label": "6 cluster per month, 4 per cluster",
        "Type": "reference"
      }
    }
  ],
  "json_export": {
    "source_row_index": 10909,
    "clinic_date": "KINGS NEUROSCIENCES CENTRE\n\nClinic Date: 27 August 2023\n\nDr Patel\nRiverside Health Centre\n\n12 Brook Lane, Southwark, London SE1 5AB\n\nDear Dr Patel,\n\nAmelia Hart, DOB: 14-03-1987, Hospital No: H936502, NHS No. 7482195603\nFlat 3, 27 Willow Court, London SE15 3QT\n\nDiagnoses/summary: Recurrent seizures with ongoing events despite multiple prior therapies. A personalised self-management plan is documented elsewhere in the notes. Prior EEGs and imaging have been reviewed previously; no definitive structural cause identified to date.\n\nCurrent concerns and history: I reviewed Amelia Hart today following reports of variable control over recent weeks. She describes sleep disruption due to shift-pattern work and notes that when sleep is curtailed she experiences clusters of events. Specifically, over the past month she reports six clusters this month; each ~4 focal impaired-awareness seizures. She characterises these as brief episodes of behavioural arrest with automatisms, followed by fatigue and partial recall. She denies generalised convulsive activity, tongue biting, or significant injury. She also reports intermittent morning headaches which she attributes to poor sleep. No recent hospital admissions. A personalised plan for managing cluster patterns has been agreed and is recorded elsewhere in her care plan documentation.\n\nMedication history: She has previously tried levetiracetam, carbamazepine, valproate, gabapentin, phenytoin, phenobarbital, lacosamide, and clobazam with limited durability of benefit and/or side effects (notably fatigue and mood symptoms with some agents). She has not used topiramate, zonisamide, or perampanel. No known drug allergies.\n\nCurrent medications: Lamotrigine 100 mg twice daily; folic acid 5 mg daily; metoclopramide as required for nausea. She uses a reminder app and pill organiser; adherence appears good by her report.\n\nExamination and tests: Neurological examination today was non-focal. Blood pressure 118/72 mmHg, pulse 72 bpm. Weight stable. Recent routine bloods (U&E, LFT, FBC) recorded in primary care last month were within reference ranges. No new imaging performed since prior normal MRI report on file.\n\nDiscussion: We reviewed triggers and her personalised plan, focusing on sleep hygiene, safety during periods of increased risk, and when to seek urgent help. She reports occasional cluster patterns linked to sleep loss and is aware of the early signs. She prefers to optimise non-pharmacological measures first and keep medication options under review. We discussed potential future options, including consideration of agents not yet trialled, and agreed no immediate change today given recent stability between clusters and her wish to continue monitoring.\n\nPlan:\n- Continue current lamotrigine dose for now; no change today.\n- Reinforce sleep and routine measures as per personalised plan; patient has written guidance and emergency contact numbers.\n- Provide seizure diary template integrated with her reminder app; she will document timing relative to sleep and any missed doses.\n- Arrange epilepsy specialist nurse telephone review in 4–6 weeks to reassess frequency and impact of clusters and to revisit treatment choices if events persist.\n- Safety advice updated: bathing supervision avoided, preferred showers; cooking with caution during periods of increased risk; avoid heights and open water when sleep-deprived.\n- Routine clinic follow-up in 4 months, with an option for earlier review if cluster frequency increases or injuries occur.\n\nYours sincerely,",
    "labels_match_all_categories": true,
    "quotes_ok_all_categories": true,
    "row_ok": true,
    "mismatch_categories": "",
    "quote_issue_categories": "",
    "check__Seizure Frequency Number": {
      "analysis": "The letter explicitly states: \"over the past month she reports six clusters this month; each ~4 focal impaired-awareness seizures.\" This provides a clear numeric frequency for clusters per month and seizures per cluster. No other differing frequency is provided. Therefore, select the highest specificity label format for clusters with per-cluster count.\nCalculation: 6 clusters in 1 month; 4 per cluster.",
      "seizure_frequency_number": [
        "6 cluster per month, 4 per cluster",
        "over the past month she reports six clusters this month; each ~4 focal impaired-awareness seizures."
      ],
      "reference": [
        "6 cluster per month, 4 per cluster",
        "six clusters this month; each ~4 focal impaired-awareness seizures"
      ]
    }
  },
  "overlaps": [],
  "temporal_sparse": [],
  "incomplete_meds": [],
  "timeline_events": [],
  "type_counts": {
    "SeizureFrequency": 2
  },
  "flaws": [],
  "negated_entities": [],
  "low_certainty": [],
  "has_unknown_seizure": false
}