{
  "id": "gan_79",
  "text": "KINGS NEUROSCIENCES CENTRE\n\n\nClinic Date: 02 October 2025\n\nDr A. Patel\nCity Gate Health Centre\n\n12 City Gate, London EC1A 4ZZ\nDear Dr A. Patel\nMr Daniel Hughes, DOB: 14-03-1986, Hospital No: H928374 NHS No. 8473926150\nFlat 3, 29 Fleet Street, London EC4Y 1AA \n\nDiagnoses/summary: Combined generalised and focal epilepsy type – patient reports features of both generalised seizures (brief absences and occasional generalised tonic–clonic events) and focal aware/aware-impaired episodes with temporal features. Seizure frequency currently reported as ≤ 6 to 7 per year, typically clustering around periods of jet lag and sleep loss related to frequent business travel across time zones. Appointments are often conducted by telephone due to travel schedule.\n\nMRI brain (2018): structurally normal; no definite epileptogenic lesion identified.\nEEG (2020, routine): generalised spike–wave activity with intermittent left temporal sharp waves; photic stimulation unremarkable.\n\nPrevious medication: Sodium valproate (weight gain, tremor), carbamazepine (dizziness, hyponatraemia), levetiracetam (mood irritability), clobazam PRN for travel-related clusters, lamotrigine (partial benefit), lacosamide (no clear benefit), topiramate (cognitive slowing), zonisamide (insomnia), perampanel (mood change).\n\nNot taken: brivaracetam, cenobamate, eslicarbazepine, rufinamide, vigabatrin, tiagabine, pregabalin, primidone.\n\nComorbidities: Migraine without aura (stress/sleep-loss related). No known cardiac disease. No history of status epilepticus.\n\nI reviewed Mr Daniel Hughes via a scheduled telephone clinic today, as he is currently travelling for work. He reports his seizure burden remains ≤ 6 to 7 per year, with a recognisable pattern: brief focal aware episodes with déjà vu and epigastric rising lasting under a minute, and rarer generalised tonic–clonic seizures typically following multiple long-haul flights. He describes occasional brief absences noted by colleagues during videoconferences. He keeps a diary correlating events with irregular sleep, overnight flights, and caffeine excess. No injuries. No hospital admissions since last review.\n\nCurrent medicines:\n- Lamotrigine 150 mg twice daily\n- Brivaracetam 100 mg twice daily (initiated abroad three months ago; self-reported better tolerability than levetiracetam)\n- Clobazam 10 mg at night PRN for travel weeks (1–3 nights around long-haul flights)\n- Riboflavin 200 mg daily for migraine prophylaxis (self-initiated)\n\nTravel and lifestyle context: Works across Europe, the US, and Asia with frequent time zone shifts. Uses airline pre-boarding to reduce stress, wears medical ID, and adheres to local driving restrictions when abroad. Reports good medication adherence using phone reminders, but missed two doses in the last quarter during a delayed connection. Sleep remains irregular on multi-sector trips.\n\nPlan:\n- Continue lamotrigine and brivaracetam at current doses given tolerability and seizure frequency of ≤ 6 to 7 per year. Reinforced adherence strategies during flight disruptions (carry-on blister packs, duplicate alarm prompts, and setting local-time conversion reminders).\n- Clobazam PRN limited to travel-associated high-risk periods; advised on sedation risk and avoidance of alcohol when used.\n- Agreed to trial structured sleep hygiene across time zones (patient-led): maintaining dark/light cues, limiting late caffeine, and scheduling short naps on arrival days based on local time; patient prefers non-pharmacological measures.\n- Safety: reiterated water precautions, working at height, and local regulations for driving post-seizure when abroad; patient confirms compliance.\n- Investigations: No immediate further imaging required. If breakthrough frequency increases or semiology changes, consider prolonged ambulatory EEG to characterise both generalised and focal events during travel periods.\n- Follow-up: Telephone review in 4 months or earlier if two or more events occur within a month. Patient will forward seizure diary screenshots monthly via secure portal.\n\nThank you for your ongoing care and for assisting with prescription continuity while he is overseas. Please contact me if any issues arise.\n\nYours sincerely",
  "entities": [
    {
      "id": "T_gold",
      "type": "SeizureFrequency",
      "start": 509,
      "end": 566,
      "text": "Seizure frequency currently reported as ≤ 6 to 7 per year",
      "attributes": {
        "Label": "6 to 7 per year",
        "Type": "gold"
      }
    },
    {
      "id": "T_ref",
      "type": "SeizureFrequency",
      "start": 549,
      "end": 566,
      "text": "≤ 6 to 7 per year",
      "attributes": {
        "Label": "6 to 7 per year",
        "Type": "reference"
      }
    }
  ],
  "json_export": {
    "source_row_index": 79,
    "clinic_date": "KINGS NEUROSCIENCES CENTRE\n\n\nClinic Date: 02 October 2025\n\nDr A. Patel\nCity Gate Health Centre\n\n12 City Gate, London EC1A 4ZZ\nDear Dr A. Patel\nMr Daniel Hughes, DOB: 14-03-1986, Hospital No: H928374 NHS No. 8473926150\nFlat 3, 29 Fleet Street, London EC4Y 1AA \n\nDiagnoses/summary: Combined generalised and focal epilepsy type – patient reports features of both generalised seizures (brief absences and occasional generalised tonic–clonic events) and focal aware/aware-impaired episodes with temporal features. Seizure frequency currently reported as ≤ 6 to 7 per year, typically clustering around periods of jet lag and sleep loss related to frequent business travel across time zones. Appointments are often conducted by telephone due to travel schedule.\n\nMRI brain (2018): structurally normal; no definite epileptogenic lesion identified.\nEEG (2020, routine): generalised spike–wave activity with intermittent left temporal sharp waves; photic stimulation unremarkable.\n\nPrevious medication: Sodium valproate (weight gain, tremor), carbamazepine (dizziness, hyponatraemia), levetiracetam (mood irritability), clobazam PRN for travel-related clusters, lamotrigine (partial benefit), lacosamide (no clear benefit), topiramate (cognitive slowing), zonisamide (insomnia), perampanel (mood change).\n\nNot taken: brivaracetam, cenobamate, eslicarbazepine, rufinamide, vigabatrin, tiagabine, pregabalin, primidone.\n\nComorbidities: Migraine without aura (stress/sleep-loss related). No known cardiac disease. No history of status epilepticus.\n\nI reviewed Mr Daniel Hughes via a scheduled telephone clinic today, as he is currently travelling for work. He reports his seizure burden remains ≤ 6 to 7 per year, with a recognisable pattern: brief focal aware episodes with déjà vu and epigastric rising lasting under a minute, and rarer generalised tonic–clonic seizures typically following multiple long-haul flights. He describes occasional brief absences noted by colleagues during videoconferences. He keeps a diary correlating events with irregular sleep, overnight flights, and caffeine excess. No injuries. No hospital admissions since last review.\n\nCurrent medicines:\n- Lamotrigine 150 mg twice daily\n- Brivaracetam 100 mg twice daily (initiated abroad three months ago; self-reported better tolerability than levetiracetam)\n- Clobazam 10 mg at night PRN for travel weeks (1–3 nights around long-haul flights)\n- Riboflavin 200 mg daily for migraine prophylaxis (self-initiated)\n\nTravel and lifestyle context: Works across Europe, the US, and Asia with frequent time zone shifts. Uses airline pre-boarding to reduce stress, wears medical ID, and adheres to local driving restrictions when abroad. Reports good medication adherence using phone reminders, but missed two doses in the last quarter during a delayed connection. Sleep remains irregular on multi-sector trips.\n\nPlan:\n- Continue lamotrigine and brivaracetam at current doses given tolerability and seizure frequency of ≤ 6 to 7 per year. Reinforced adherence strategies during flight disruptions (carry-on blister packs, duplicate alarm prompts, and setting local-time conversion reminders).\n- Clobazam PRN limited to travel-associated high-risk periods; advised on sedation risk and avoidance of alcohol when used.\n- Agreed to trial structured sleep hygiene across time zones (patient-led): maintaining dark/light cues, limiting late caffeine, and scheduling short naps on arrival days based on local time; patient prefers non-pharmacological measures.\n- Safety: reiterated water precautions, working at height, and local regulations for driving post-seizure when abroad; patient confirms compliance.\n- Investigations: No immediate further imaging required. If breakthrough frequency increases or semiology changes, consider prolonged ambulatory EEG to characterise both generalised and focal events during travel periods.\n- Follow-up: Telephone review in 4 months or earlier if two or more events occur within a month. Patient will forward seizure diary screenshots monthly via secure portal.\n\nThank you for your ongoing care and for assisting with prescription continuity while he is overseas. Please contact me if any issues arise.\n\nYours sincerely",
    "labels_match_all_categories": true,
    "quotes_ok_all_categories": true,
    "row_ok": true,
    "mismatch_categories": "",
    "quote_issue_categories": "",
    "check__Seizure Frequency Number": {
      "analysis": "The letter explicitly states the patient's current seizure frequency multiple times as \"≤ 6 to 7 per year\" and \"seizure burden remains ≤ 6 to 7 per year.\" There are no other conflicting frequencies given. According to the rules, we should use explicit numeric expressions and normalize to allowed formats. The appropriate normalization is a yearly frequency as a numeric range: \"6 to 7 per year.\" The leading \"≤\" suggests an upper bound, but the closest allowed format is the numeric range given. No clustering details with counts per cluster are provided that would override the annual rate.",
      "seizure_frequency_number": [
        "6 to 7 per year",
        "Seizure frequency currently reported as ≤ 6 to 7 per year"
      ],
      "reference": [
        "6 to 7 per year",
        "≤ 6 to 7 per year"
      ]
    }
  },
  "overlaps": [],
  "temporal_sparse": [],
  "incomplete_meds": [],
  "timeline_events": [],
  "type_counts": {
    "SeizureFrequency": 2
  },
  "flaws": [],
  "negated_entities": [],
  "low_certainty": [],
  "has_unknown_seizure": false
}